promptpay/__init__.py
promptpay/__main__.py
promptpay/qrcode.py
promptpay-1.1.9.dist-info/LICENSE
promptpay-1.1.9.dist-info/METADATA
promptpay-1.1.9.dist-info/WHEEL
promptpay-1.1.9.dist-info/entry_points.txt
promptpay-1.1.9.dist-info/top_level.txt
promptpay-1.1.9.dist-info/RECORD
