Metadata-Version: 2.1
Name: promptpay
Version: 1.1.9
Summary: Python library to generate PromptPay QR Code
Home-page: https://github.com/jojoee/promptpay
Author: Nathachai Thongniran
Author-email: inid3a@gmail.com
License: MIT
Keywords: promptpay,qrcode
Platform: UNKNOWN
Classifier: License :: OSI Approved :: MIT License
Classifier: Operating System :: OS Independent
Classifier: Programming Language :: Python :: 3
Classifier: Programming Language :: Python :: 3.5
Classifier: Programming Language :: Python :: 3.6
Classifier: Programming Language :: Python :: 3.7
Classifier: Programming Language :: Python :: 3.8
Classifier: Programming Language :: Python :: 3.9
License-File: LICENSE
